fake_useragent/__init__.py
fake_useragent/errors.py
fake_useragent/fake.py
fake_useragent/log.py
fake_useragent/settings.py
fake_useragent/utils.py
fake_useragent/data/browsers.json
fake_useragent/data/chrome.jpg
useregent_generator-1.6.5.dist-info/AUTHORS
useregent_generator-1.6.5.dist-info/LICENSE
useregent_generator-1.6.5.dist-info/METADATA
useregent_generator-1.6.5.dist-info/WHEEL
useregent_generator-1.6.5.dist-info/top_level.txt
useregent_generator-1.6.5.dist-info/RECORD
