Metadata-Version: 2.1
Name: useregent-generator
Version: 1.6.5
Summary: Up-to-date simple useragent faker with real world database
Project-URL: Homepage, https://github.com/
Keywords: user,agent,user agent,useragent
Classifier: Development Status :: 5 - Production/Stable
Classifier: Intended Audience :: Developers
Classifier: License :: OSI Approved :: Apache Software License
Classifier: Operating System :: POSIX
Classifier: Operating System :: MacOS :: MacOS X
Classifier: Operating System :: Microsoft :: Windows
Classifier: Programming Language :: Python
Classifier: Programming Language :: Python :: 3
Classifier: Programming Language :: Python :: 3 :: Only
Classifier: Operating System :: OS Independent
Classifier: Topic :: Internet :: WWW/HTTP
Classifier: Topic :: Software Development
Classifier: Topic :: Software Development :: Libraries :: Python Modules
Classifier: Topic :: Utilities
License-File: LICENSE
License-File: AUTHORS
Requires-Dist: importlib-resources >=5.0 ; python_version < "3.10"
Requires-Dist: importlib-metadata ~=4.0 ; python_version < "3.8"
